requisite_check/RequisiteCheck.py
requisite_check/RequisiteCheckResult.py
requisite_check/__init__.py
requisite_check-0.1.0.dist-info/WHEEL
requisite_check-0.1.0.dist-info/METADATA
requisite_check-0.1.0.dist-info/RECORD
