Metadata-Version: 2.1
Name: requisite-check
Version: 0.1.0
Summary: Module for working with course requisite data and checking requisite satisfaciton.
Author: Michael Hickman
Author-email: mhickman@unm.edu
Requires-Python: >=3.10,<4.0
Classifier: Programming Language :: Python :: 3
Classifier: Programming Language :: Python :: 3.10
Classifier: Programming Language :: Python :: 3.11
